{
  "settings": {
    "migrated": true,
    "iconPacksPath": ".obsidian/icons",
    "fontSize": 16,
    "emojiStyle": "native",
    "iconColor": null,
    "recentlyUsedIcons": [
      "FasList",
      "RiStickyNoteLine",
      "Fas7",
      "FarNoteSticky",
      "RiLink"
    ],
    "recentlyUsedIconsSize": 5,
    "rules": [],
    "extraMargin": {
      "top": 0,
      "right": 4,
      "bottom": 0,
      "left": 0
    }
  },
  "Customers/Confluent": "SiApachekafka",
  "Customers/ING": "IbBank",
  "Projects": "FasGear",
  "Customers": "RiSuitcaseLine",
  "References": "RiLink",
  "Zettelkasten": "RiStickyNoteLine",
  "Weekly": "Fas7",
  "MOC": "FasList"
}